{"nodes": [{"id": "src_components_providers_settings_context_tsx", "label": "settings-context.tsx", "file_type": "code", "source_file": "src\\components\\providers\\settings-context.tsx", "source_location": "L1"}, {"id": "settings_context_usesettings", "label": "useSettings()", "file_type": "code", "source_file": "src\\components\\providers\\settings-context.tsx", "source_location": "L24"}, {"id": "settings_context_settingsprovider", "label": "SettingsProvider()", "file_type": "code", "source_file": "src\\components\\providers\\settings-context.tsx", "source_location": "L31"}], "edges": [{"source": "src_components_providers_settings_context_tsx", "target": "react", "relation": "imports_from", "confidence": "EXTRACTED", "source_file": "src\\components\\providers\\settings-context.tsx", "source_location": "L3", "weight": 1.0}, {"source": "src_components_providers_settings_context_tsx", "target": "settings", "relation": "imports_from", "confidence": "EXTRACTED", "source_file": "src\\components\\providers\\settings-context.tsx", "source_location": "L4", "weight": 1.0}, {"source": "src_components_providers_settings_context_tsx", "target": "settings_context_usesettings", "relation": "contains", "confidence": "EXTRACTED", "source_file": "src\\components\\providers\\settings-context.tsx", "source_location": "L24", "weight": 1.0}, {"source": "src_components_providers_settings_context_tsx", "target": "settings_context_settingsprovider", "relation": "contains", "confidence": "EXTRACTED", "source_file": "src\\components\\providers\\settings-context.tsx", "source_location": "L31", "weight": 1.0}]}